dataset_tools/__init__.py
dataset_tools/convert/__init__.py
dataset_tools/convert/cityscapes/__init__.py
dataset_tools/convert/cityscapes/main.py
dataset_tools/convert/coco/__init__.py
dataset_tools/convert/coco/main.py
dataset_tools/convert/pascal/__init__.py
dataset_tools/convert/pascal/main.py
dataset_tools/data/__init__.py
dataset_tools/data/download_urls/__init__.py
dataset_tools/data/download_urls/released_datasets.json
dataset_tools/fonts/FiraSans-Black.ttf
dataset_tools/fonts/FiraSans-BlackItalic.ttf
dataset_tools/fonts/FiraSans-Bold.ttf
dataset_tools/fonts/FiraSans-BoldItalic.ttf
dataset_tools/fonts/FiraSans-ExtraBold.ttf
dataset_tools/fonts/FiraSans-ExtraBoldItalic.ttf
dataset_tools/fonts/FiraSans-ExtraLight.ttf
dataset_tools/fonts/FiraSans-ExtraLightItalic.ttf
dataset_tools/fonts/FiraSans-Italic.ttf
dataset_tools/fonts/FiraSans-Light.ttf
dataset_tools/fonts/FiraSans-LightItalic.ttf
dataset_tools/fonts/FiraSans-Medium.ttf
dataset_tools/fonts/FiraSans-MediumItalic.ttf
dataset_tools/fonts/FiraSans-Regular.ttf
dataset_tools/fonts/FiraSans-SemiBold.ttf
dataset_tools/fonts/FiraSans-SemiBoldItalic.ttf
dataset_tools/fonts/FiraSans-Thin.ttf
dataset_tools/fonts/FiraSans-ThinItalic.ttf
dataset_tools/image/__init__.py
dataset_tools/image/renders/__init__.py
dataset_tools/image/renders/convert.py
dataset_tools/image/renders/horizontal_grid.py
dataset_tools/image/renders/poster.py
dataset_tools/image/renders/previews.py
dataset_tools/image/renders/separated_anns_grid.py
dataset_tools/image/renders/vertical_grid.py
dataset_tools/image/renders/wrapper.py
dataset_tools/image/stats/__init__.py
dataset_tools/image/stats/basestats.py
dataset_tools/image/stats/class_balance.py
dataset_tools/image/stats/class_cooccurrence.py
dataset_tools/image/stats/classes_per_image.py
dataset_tools/image/stats/datasets_annotations.py
dataset_tools/image/stats/heatmaps_for_classes.py
dataset_tools/image/stats/object_and_class_sizes.py
dataset_tools/image/stats/objects_distribution.py
dataset_tools-0.1.9.dist-info/LICENSE
dataset_tools-0.1.9.dist-info/METADATA
dataset_tools-0.1.9.dist-info/WHEEL
dataset_tools-0.1.9.dist-info/top_level.txt
dataset_tools-0.1.9.dist-info/RECORD
