Metadata-Version: 2.1
Name: dataset-tools
Version: 0.1.9
Summary: Dataset tools for dataset ninja made by Supervisely team.
Home-page: https://github.com/supervisely/dataset-tools
Author: Supervisely
Author-email: support@supervise.ly
Classifier: Development Status :: 5 - Production/Stable
Classifier: Intended Audience :: Developers
Classifier: Intended Audience :: Science/Research
Classifier: Natural Language :: English
Classifier: Programming Language :: Python :: 3.7
Classifier: Programming Language :: Python :: 3.8
Classifier: Programming Language :: Python :: 3.9
Classifier: Programming Language :: Python :: 3.10
Classifier: Topic :: Scientific/Engineering :: Artificial Intelligence
Classifier: Topic :: Software Development :: Libraries :: Python Modules
Requires-Python: >=3.7.1
License-File: LICENSE
Requires-Dist: supervisely>=6.72.28
Requires-Dist: numpy<2.0.0,>=1.19
Requires-Dist: requests<3.0.0,>=2.27.1
Requires-Dist: requests-toolbelt<1.0.0,>=0.9.1
Requires-Dist: tqdm<5.0.0,>=4.62.3
Requires-Dist: pandas<=1.5.2,>=1.1.3
Requires-Dist: matplotlib<4.0.0,>=3.3.2
Requires-Dist: scikit-image<1.0.0,>=0.17.1
Requires-Dist: dataframe-image<1.0.0,>=0.1.11
Requires-Dist: inflect>=6.0.0
Requires-Dist: gdown>=4.7.1
Requires-Dist: urllib3==1.26.15
Requires-Dist: geojson>=3.0.0
Requires-Dist: titlecase>=2.4.1
Requires-Dist: pycocotools>=2.0.0
Requires-Dist: memory-profiler==0.61.0
Requires-Dist: Pympler==1.0.1
Requires-Dist: xmltodict==0.13.0
Requires-Dist: imagesize==1.4.1
Provides-Extra: docs
Requires-Dist: sphinx==4.4.0; extra == "docs"
Requires-Dist: jinja2==3.0.3; extra == "docs"
Requires-Dist: sphinx-immaterial==0.4.0; extra == "docs"
Requires-Dist: sphinx-copybutton==0.4.0; extra == "docs"
Requires-Dist: sphinx-autodoc-typehints==1.15.3; extra == "docs"
Requires-Dist: sphinxcontrib-details-directive==0.1.0; extra == "docs"
Requires-Dist: myst-parser==0.18.0; extra == "docs"
